general_utils/__init__.py
general_utils/utils.py
general_utils-0.1.16.dist-info/METADATA
general_utils-0.1.16.dist-info/WHEEL
general_utils-0.1.16.dist-info/top_level.txt
general_utils-0.1.16.dist-info/RECORD
