Metadata-Version: 2.1
Name: general-utils
Version: 0.1.16
Summary: A general package that has useful functionalities
Home-page: https://github.com/kashy750/python_package
Author: Kashyap Madariyil
Author-email: kashyapmadariyil@gmail.com
License: UNKNOWN
Platform: UNKNOWN
Classifier: Programming Language :: Python :: 3.7
Classifier: License :: OSI Approved :: GNU General Public License v3 (GPLv3)
Requires-Dist: pika (>=1.1.0)
Requires-Dist: minio (>=5.0.10)
Requires-Dist: redis (>=3.4.1)
Requires-Dist: pandas (>=1.0.1)
Requires-Dist: pyarrow (>=0.17.0)
Requires-Dist: grequests (>=0.6.0)
Requires-Dist: requests (>=2.23.0)
Requires-Dist: openpyxl (>=3.0.5)
Requires-Dist: azure-storage-blob (>=12.5.0)
Requires-Dist: sentry-sdk (>=1.0.0)
